Metadata-Version: 2.4
Name: co-gym
Version: 0.1.5
Summary: Framework and toolkits for building and evaluating collaborative agents that can work together with humans
Author-email: Yijia Shao <shaoyj@stanford.edu>, Vinay Samuel <vsamuel@umd.edu>
Maintainer-email: Yijia Shao <shaoyj@stanford.edu>, Vinay Samuel <vsamuel@umd.edu>
License-Expression: MIT
Project-URL: Homepage, https://cogym.saltlab.stanford.edu/
Project-URL: Repository, https://github.com/SALT-NLP/collaborative-gym
Project-URL: Documentation, https://cogym.saltlab.stanford.edu/
Project-URL: Bug Tracker, https://github.com/SALT-NLP/collaborative-gym/issues
Keywords: collaborative-ai,multi-agent,human-ai-collaboration,reinforcement-learning
Classifier: Development Status :: 3 - Alpha
Classifier: Intended Audience :: Developers
Classifier: Intended Audience :: Science/Research
Classifier: Topic :: Scientific/Engineering :: Artificial Intelligence
Classifier: Programming Language :: Python :: 3
Classifier: Programming Language :: Python :: 3.8
Classifier: Programming Language :: Python :: 3.9
Classifier: Programming Language :: Python :: 3.10
Classifier: Programming Language :: Python :: 3.11
Requires-Python: >=3.11
License-File: LICENSE
Requires-Dist: autogen
Requires-Dist: ag2[jupyter-executor]
Requires-Dist: httpx<0.28.0,>=0.23.0
Requires-Dist: litellm>=1.59.3
Requires-Dist: knowledge-storm>=0.2.8
Requires-Dist: rstr
Requires-Dist: gymnasium
Requires-Dist: prompt-toolkit
Requires-Dist: websocket-client>=1.7.0
Requires-Dist: jupyter
Requires-Dist: aact>=0.0.10
Requires-Dist: typer
Requires-Dist: pydantic<3.0.0,>=2.8.0
Requires-Dist: fastapi
Requires-Dist: docker
Requires-Dist: pygments
Requires-Dist: datasets
Requires-Dist: scikit-learn
Requires-Dist: PyPDF2
Requires-Dist: uvicorn[standard]
Requires-Dist: arxiv
Requires-Dist: googlemaps
Requires-Dist: voyageai
Requires-Dist: python-multipart
Requires-Dist: anthropic
Requires-Dist: apscheduler
Provides-Extra: dev
Requires-Dist: pytest>=6.0; extra == "dev"
Requires-Dist: black>=22.0; extra == "dev"
Requires-Dist: flake8>=4.0; extra == "dev"
Requires-Dist: mypy>=0.950; extra == "dev"
Provides-Extra: docs
Requires-Dist: sphinx>=4.0; extra == "docs"
Requires-Dist: sphinx-rtd-theme>=1.0; extra == "docs"
Dynamic: license-file
